yolov8tohf/__init__.py
yolov8tohf/cli.py
yolov8tohf/hf_utils.py
yolov8tohf/ultralytics_utils.py
yolov8tohf-0.0.2.dist-info/LICENSE
yolov8tohf-0.0.2.dist-info/METADATA
yolov8tohf-0.0.2.dist-info/WHEEL
yolov8tohf-0.0.2.dist-info/entry_points.txt
yolov8tohf-0.0.2.dist-info/top_level.txt
yolov8tohf-0.0.2.dist-info/RECORD
